nanonis_tramea/NanonisClass.py
nanonis_tramea/__init__.py
nanonis_tramea_examples/Example_Custom2DSweep_1DSweeper.py
nanonis_tramea_examples/Example_CustomUOSweep.py
nanonis_tramea_examples/Example_LockInSweep.py
nanonis_tramea_examples/Example_SimpleSignalAcquisition.py
nanonis_tramea-1.0.7.dist-info/METADATA
nanonis_tramea-1.0.7.dist-info/WHEEL
nanonis_tramea-1.0.7.dist-info/licenses/LICENSE
nanonis_tramea-1.0.7.dist-info/RECORD
