Metadata-Version: 2.4
Name: nanonis_tramea
Version: 1.0.7
Summary: Python package for controlling Nanonis Tramea software through python
Author-email: Samuel O'Neill <support@specs-zurich.com>
Maintainer-email: Aitziber Herrero <support@specs-zurich.com>
License-File: LICENSE
Classifier: Operating System :: OS Independent
Classifier: Programming Language :: Python :: 3
Requires-Python: >=3.8
